{"type": "Startpoints", "instance_name": "us-night-0000045", "points": [{"x": 14678.0, "y": 4417.0}, {"x": 11374.0, "y": 8128.0}, {"x": 7496.0, "y": 5576.0}, {"x": 10989.0, "y": 6884.0}, {"x": 13998.0, "y": 6086.0}, {"x": 4566.0, "y": 4750.0}, {"x": 14999.0, "y": 7169.0}, {"x": 12442.0, "y": 7617.0}, {"x": 9112.0, "y": 2862.0}, {"x": 10806.0, "y": 3360.0}, {"x": 13433.0, "y": 5407.0}, {"x": 8345.0, "y": 3397.0}, {"x": 9006.0, "y": 4358.0}, {"x": 8214.0, "y": 3212.0}, {"x": 8035.0, "y": 3449.0}]}